README.rst
setup.py
docs/HISTORY.txt
fullmarks/__init__.py
fullmarks.tinymceplugins.asciisvg.egg-info/PKG-INFO
fullmarks.tinymceplugins.asciisvg.egg-info/SOURCES.txt
fullmarks.tinymceplugins.asciisvg.egg-info/dependency_links.txt
fullmarks.tinymceplugins.asciisvg.egg-info/entry_points.txt
fullmarks.tinymceplugins.asciisvg.egg-info/namespace_packages.txt
fullmarks.tinymceplugins.asciisvg.egg-info/not-zip-safe
fullmarks.tinymceplugins.asciisvg.egg-info/requires.txt
fullmarks.tinymceplugins.asciisvg.egg-info/top_level.txt
fullmarks/tinymceplugins/__init__.py
fullmarks/tinymceplugins/asciisvg/__init__.py
fullmarks/tinymceplugins/asciisvg/configure.zcml
fullmarks/tinymceplugins/asciisvg/profiles.zcml
fullmarks/tinymceplugins/asciisvg/setuphandlers.py
fullmarks/tinymceplugins/asciisvg/skins.zcml
fullmarks/tinymceplugins/asciisvg/profiles/default/cssregistry.xml
fullmarks/tinymceplugins/asciisvg/profiles/default/fullmarks.tinymceplugins.asciisvg_various.txt
fullmarks/tinymceplugins/asciisvg/profiles/default/import_steps.xml
fullmarks/tinymceplugins/asciisvg/profiles/default/jsregistry.xml
fullmarks/tinymceplugins/asciisvg/profiles/default/metadata.xml
fullmarks/tinymceplugins/asciisvg/profiles/default/skins.xml
fullmarks/tinymceplugins/asciisvg/profiles/default/tinymce.xml
fullmarks/tinymceplugins/asciisvg/skins/tinymce_plugin_asciisvg/asciisvg/asciisvgdlg.htm.pt
fullmarks/tinymceplugins/asciisvg/skins/tinymce_plugin_asciisvg/asciisvg/editor_plugin.js
fullmarks/tinymceplugins/asciisvg/skins/tinymce_plugin_asciisvg/asciisvg/css/asciisvg.css
fullmarks/tinymceplugins/asciisvg/skins/tinymce_plugin_asciisvg/asciisvg/img/Thumbs.db
fullmarks/tinymceplugins/asciisvg/skins/tinymce_plugin_asciisvg/asciisvg/img/ed_asciisvg.gif
fullmarks/tinymceplugins/asciisvg/skins/tinymce_plugin_asciisvg/asciisvg/js/ASCIIMathML.js
fullmarks/tinymceplugins/asciisvg/skins/tinymce_plugin_asciisvg/asciisvg/js/ASCIIsvgPI.js
fullmarks/tinymceplugins/asciisvg/skins/tinymce_plugin_asciisvg/asciisvg/js/asciisvg.js
fullmarks/tinymceplugins/asciisvg/skins/tinymce_plugin_asciisvg/asciisvg/js/asciisvgdlg.js
fullmarks/tinymceplugins/asciisvg/skins/tinymce_plugin_asciisvg/asciisvg/js/d.svg.pt
fullmarks/tinymceplugins/asciisvg/skins/tinymce_plugin_asciisvg/asciisvg/langs/en.js
fullmarks/tinymceplugins/asciisvg/skins/tinymce_plugin_asciisvg/asciisvg/langs/en_dlg.js
fullmarks/tinymceplugins/asciisvg/static/asciisvg.js