Metadata-Version: 1.0
Name: fullmarks.tinymceplugins.asciisvg
Version: 1.3
Summary: ASCIISvg Plugin for TinyMCE in Plone for drawing a graph of function in SVG
Home-page: http://github.com/fullmarks/fullmarks.tinymceplugins.asciisvg
Author: roche@upfrontsystems.co.za
Author-email: UNKNOWN
License: GPL
Keywords: svg mathematics plone
Platform: UNKNOWN
Classifier: Programming Language :: Python
Classifier: Framework :: Plone
